[
  {
    "slug": "marketing-leader-at-an-smb-communications-saas",
    "url": "https://www.fractionaljobs.io/jobs/marketing-leader-at-an-smb-communications-saas",
    "title": "Marketing Leader",
    "company": "An SMB Communications SaaS",
    "category": "Marketing",
    "hours": "10 - 20 hrs",
    "rate": "$10K / month",
    "location": "Remote (Worldwide)",
    "remote": true,
    "posted": "April 29, 2026",
    "source": "fractionaljobs",
    "date_scraped": "2026-04-29",
    "flagged": false
  }
]