[
  {
    "slug": "chief-financial-officer-at-a-funds-distribution-govtech-service",
    "url": "https://www.fractionaljobs.io/jobs/chief-financial-officer-at-a-funds-distribution-govtech-service",
    "title": "Chief Financial Officer",
    "company": "A Funds Distribution GovTech Service",
    "category": "Finance",
    "hours": "10 - 20 hrs",
    "rate": "$200 - $250 / hr",
    "location": "Remote (USA only)",
    "remote": true,
    "posted": "June 17, 2026",
    "source": "fractionaljobs",
    "date_scraped": "2026-06-18",
    "flagged": false
  }
]