[
  {
    "slug": "vp-government-affairs-at-a-senior-care-advisory-firm",
    "url": "https://www.fractionaljobs.io/jobs/vp-government-affairs-at-a-senior-care-advisory-firm",
    "title": "VP, Government Affairs",
    "company": "A Senior Care Advisory Firm",
    "category": "Other",
    "hours": "8 - 25 hrs",
    "rate": "$180 - $250 / hr",
    "location": "Remote (USA only)",
    "remote": true,
    "posted": "June 18, 2026",
    "source": "fractionaljobs",
    "date_scraped": "2026-06-19",
    "flagged": false
  }
]