[
  {
    "slug": "lever-firstup-mobile-ux-designer-lever",
    "url": "https://www.gofractional.com/job/lever-firstup-mobile-ux-designer-lever",
    "title": "Mobile UX Designer",
    "company": "Firstup",
    "location": "Remote - US + UK",
    "rate": "$50-$80/hr",
    "hours": "20-40 hrs/wk",
    "posted": "2026-06-26",
    "source": "gofractional",
    "date_scraped": "2026-06-27",
    "flagged": true
  },
  {
    "slug": "welcometothejungle-clio-graphic-designer-welcome-to-the-jungle-formerly-otta",
    "url": "https://www.gofractional.com/job/welcometothejungle-clio-graphic-designer-welcome-to-the-jungle-formerly-otta",
    "title": "Graphic Designer",
    "company": "Clio",
    "location": "Remote - Vancouver, British Columbia, Canada",
    "rate": "$85-$130/hr",
    "hours": "30-40 hrs/wk",
    "posted": "2026-06-26",
    "source": "gofractional",
    "date_scraped": "2026-06-27",
    "flagged": true
  }
]